_optcc.cpython-36m-x86_64-linux-gnu.so
optcc/__init__.py
optcc/optcc.i
optcc/optcc.py
optcc/C/optcc.c
optcc/C/gclgms.c
optcc/C/gcmt.c
optcc/C/gcmt.h
optcc/C/optcc.h
optcc/C/optcc_wrap.c
optcc/C/gclgms.h
optcc-4.33.20.post1.dist-info/RECORD
optcc-4.33.20.post1.dist-info/METADATA
optcc-4.33.20.post1.dist-info/top_level.txt
optcc-4.33.20.post1.dist-info/WHEEL
optcc-4.33.20.post1.dist-info/LICENSE
