Metadata-Version: 2.1
Name: optcc
Version: 4.33.20.post1
Summary: Python library to access GAMS Option Object
Home-page: https://github.com/kavvkon/gams-api
Author: GAMS Development Corp.
Maintainer: kavvkon
Maintainer-email: kavvkon@gmail.com
License: MIT
Platform: UNKNOWN
